swarmx/__init__.py
swarmx/__main__.py
swarmx/_settings.py
swarmx/agent.py
swarmx/cli.py
swarmx/edge.py
swarmx/hook.py
swarmx/mcp_client.py
swarmx/mcp_server.py
swarmx/quota.py
swarmx/server.py
swarmx/types.py
swarmx/utils.py
swarmx/version.py
swarmx-0.7.0.dist-info/WHEEL
swarmx-0.7.0.dist-info/entry_points.txt
swarmx-0.7.0.dist-info/METADATA
swarmx-0.7.0.dist-info/RECORD
