Metadata-Version: 2.4
Name: swarmx
Version: 0.7.0
Summary: A lightweight, stateless multi-agent orchestration framework.
Author: Tang Ziya
Author-email: Tang Ziya <tcztzy@gmail.Com>
License-Expression: MIT
Classifier: Development Status :: 4 - Beta
Classifier: Intended Audience :: Developers
Classifier: Intended Audience :: Science/Research
Classifier: License :: OSI Approved :: MIT License
Classifier: Operating System :: OS Independent
Classifier: Programming Language :: Python :: 3
Classifier: Programming Language :: Python :: 3.11
Classifier: Programming Language :: Python :: 3.12
Classifier: Programming Language :: Python :: 3.13
Classifier: Programming Language :: Python :: 3.14
Classifier: Topic :: Scientific/Engineering :: Artificial Intelligence
Classifier: Topic :: Software Development :: Libraries :: Python Modules
Classifier: Topic :: System :: Distributed Computing
Classifier: Typing :: Typed
Requires-Dist: common-expression-language>=0.5.3
Requires-Dist: fastapi>=0.119.1
Requires-Dist: jinja2>=3.1.6
Requires-Dist: jsonschema>=4.25.1
Requires-Dist: markdown-it-py[plugins]>=4.0.0
Requires-Dist: mcp>=1.18.0
Requires-Dist: networkx>=3.5
Requires-Dist: openai>=2.6.0
Requires-Dist: pydantic-settings>=2.11.0
Requires-Dist: pyyaml>=6.0.3
Requires-Dist: typer>=0.20.0
Requires-Python: >=3.11
